{
    "records": [
        {
            "content": "blob:https://www.youtube.com/ab1f28f6-eb3b-46cf-9b55-ab8ec0fa7ea8",
            "type": "video"
        },
        {
            "content": "http://img1.joyreactor.cc/pics/post/%D0%B3%D0%B8%D1%84%D0%BA%D0%B8-%D0%BA%D0%BE%D1%82%D1%8D-%D1%85%D0%BE%D0%B1%D0%B0-5743291.gif",
            "type": "image"
        },
        {
            "content": "http://img1.joyreactor.cc/pics/post/%D0%BA%D0%BE%D1%82%D1%8D-%D0%BA%D0%B0%D1%80%D1%82%D0%B8%D0%BD%D0%BA%D0%B8-5744295.jpeg",
            "type": "image"
        },
        {
            "content": "http://img0.joyreactor.cc/pics/post/%D0%B3%D0%B8%D1%84%D0%BA%D0%B8-%D0%B6%D0%B8%D0%B2%D0%BD%D0%BE%D1%81%D1%82%D1%8C-%D0%BA%D0%BE%D1%82%D1%8D-%D1%87%D0%B5%D1%80%D0%B5%D0%BF%D0%B0%D1%85%D0%B0-5748180.gif",
            "type": "image"
        },
        {
            "content": "http://img1.joyreactor.cc/pics/post/%D0%B3%D0%B8%D1%84%D0%BA%D0%B8-%D0%BA%D0%BE%D1%82%D1%8D-5747159.gif",
            "type": "image"
        },
        {
            "content": "https://coub.com/view/29qhmp",
            "type": "link"
        },
        {
            "content": "https://coub.com/view/29rm16",
            "type": "link"
        },
        {
            "content": "https://www.pinterest.com/pin/306526318391378222/",
            "type": "link"
        },
        {
            "content": "https://www.pinterest.com/pin/779896860458606594/",
            "type": "link"
        },
        {
            "content": "http://img0.joyreactor.cc/pics/post/%D0%BA%D0%BE%D1%82-%D0%B6%D0%B8%D0%B2%D0%BE%D1%82%D0%BD%D1%8B%D0%B5-%D1%80%D0%B5%D0%B0%D0%BA%D1%82%D0%BE%D1%80%D0%B0-%D1%80%D0%B5%D0%B0%D0%BA%D1%82%D0%BE%D1%80-5754518.jpeg",
            "type": "image"
        },
        {
            "content": "http://img1.joyreactor.cc/pics/post/%D0%B6%D0%B8%D0%B2%D0%BD%D0%BE%D1%81%D1%82%D1%8C-%D0%BA%D0%BE%D1%82%D1%8D-%D0%BF%D0%B5%D1%81%D0%BE%D1%87%D0%BD%D0%B8%D1%86%D0%B0-5761697.jpeg",
            "type": "image"
        },
        {
            "content": "http://joyreactor.cc/post/4263759",
            "type": "link"
        },
        {
            "content": "http://img0.joyreactor.cc/pics/post/%D0%B3%D0%B8%D1%84%D0%BA%D0%B8-%D0%BA%D0%BE%D1%82-5763364.gif",
            "type": "image"
        },
        {
            "content": "http://img0.joyreactor.cc/pics/post/%D0%B3%D0%B8%D1%84%D0%BA%D0%B8-%D0%BA%D0%BE%D1%82%D1%91%D0%BD%D0%BE%D0%BA-5762276.gif",
            "type": "image"
        },
        {
            "content": "http://img0.joyreactor.cc/pics/post/%D0%BA%D0%BE%D1%82%D1%8D-5764424.jpeg",
            "type": "image"
        },
        {
            "content": "https://i.pinimg.com/564x/f3/f7/e8/f3f7e85f60b1f963157b83698ec757ba.jpg",
            "type": "image"
        },
        {
            "content": "http://img1.joyreactor.cc/pics/post/%D0%BA%D0%BE%D1%82%D1%8D-%D0%BC%D0%B0%D1%88%D0%B8%D0%BD%D0%B0-%D0%B3%D0%B8%D1%84%D0%BA%D0%B8-%D0%BF%D0%B5%D1%81%D0%BE%D1%87%D0%BD%D0%B8%D1%86%D0%B0-5765463.gif",
            "type": "image"
        },
        {
            "content": "http://joyreactor.cc/",
            "type": "link"
        },
        {
            "content": "http://img0.joyreactor.cc/pics/post/%D0%B3%D0%B8%D1%84%D0%BA%D0%B8-%D0%BA%D0%BE%D1%82%D0%B5%D0%B9%D0%BA%D0%B0-5764898.gif",
            "type": "image"
        },
        {
            "content": "http://img1.joyreactor.cc/pics/post/%D0%B3%D0%B8%D1%84%D0%BA%D0%B8-%D0%91%D0%B5%D0%B3%D0%B5%D0%BC%D0%BE%D1%82%D0%B8%D0%BA-5765105.gif",
            "type": "image"
        },
        {
            "content": "http://img0.joyreactor.cc/pics/comment/%D0%B3%D0%B8%D1%84%D0%BA%D0%B8-%D0%91%D0%B5%D0%B3%D0%B5%D0%BC%D0%BE%D1%82%D0%B8%D0%BA-3663662.gif",
            "type": "image"
        },
        {
            "content": "http://img1.joyreactor.cc/pics/post/%D0%B3%D0%B8%D1%84%D0%BA%D0%B8-%D0%B6%D0%B8%D0%B2%D0%BD%D0%BE%D1%81%D1%82%D1%8C-%D0%BA%D0%BE%D1%82%D1%8D-%D1%81%D0%BE%D0%B1%D0%B0%D0%BA%D0%B0-5768479.gif",
            "type": "image"
        },
        {
            "content": "http://img0.joyreactor.cc/pics/post/%D0%BA%D0%BE%D1%82%D1%94-%D0%BA%D1%83%D1%81%D1%8C-5767600.jpeg",
            "type": "image"
        },
        {
            "content": "http://img0.joyreactor.cc/pics/post/%D0%B3%D0%B8%D1%84%D0%BA%D0%B0-%D0%B6%D0%B8%D0%B2%D0%BD%D0%BE%D1%81%D1%82%D1%8C-%D0%BA%D0%BE%D1%82%D1%8D-5767666.gif",
            "type": "image"
        },
        {
            "content": "http://img1.joyreactor.cc/pics/post/%D0%B3%D0%B8%D1%84%D0%BA%D0%B8-%D0%BB%D1%8C%D0%B2%D1%91%D0%BD%D0%BE%D0%BA-5767707.gif",
            "type": "image"
        },
        {
            "content": "http://img1.joyreactor.cc/pics/post/%D0%B3%D0%B8%D1%84%D0%BA%D0%B8-%D0%BA%D0%BE%D1%82%D1%8D-%D1%81%D0%BE%D0%BD-5767183.gif",
            "type": "image"
        },
        {
            "content": "http://img0.joyreactor.cc/pics/post/%D0%B3%D0%B8%D1%84%D0%BA%D0%B8-%D1%81%D0%BE%D0%B1%D0%B0%D0%BA%D0%B0-%D0%B3%D1%80%D1%8F%D0%B7%D1%8C-5767326.gif",
            "type": "image"
        },
        {
            "content": "http://img1.joyreactor.cc/pics/post/%D0%B3%D0%B8%D1%84%D0%BA%D0%B0-%D0%BA%D0%BE%D1%82%D1%8D-5766791.gif",
            "type": "image"
        },
        {
            "content": "http://joyreactor.cc/post/4266047",
            "type": "link"
        },
        {
            "content": "http://img1.joyreactor.cc/pics/post/%D0%B3%D0%B8%D1%84%D0%BA%D0%B8-%D0%BA%D0%BE%D1%82%D1%8D-%D0%B2%D0%BE%D0%B4%D0%BD%D1%8B%D0%B5-%D0%BF%D1%80%D0%BE%D1%86%D0%B5%D0%B4%D1%83%D1%80%D1%8B-5768251.gif",
            "type": "image"
        },
        {
            "content": "http://img1.joyreactor.cc/pics/post/%D0%B3%D0%B8%D1%84%D0%BA%D0%B8-%D0%BA%D0%BE%D1%82%D1%8D-5768879.gif",
            "type": "image"
        },
        {
            "content": "https://www.pinterest.com/pin/712835447257840742/",
            "type": "link"
        },
        {
            "content": "http://img1.joyreactor.cc/pics/post/%D1%89%D0%B5%D0%BD%D0%BE%D0%BA-5768697.jpeg",
            "type": "image"
        },
        {
            "content": "https://www.pinterest.com/pin/364439794849851181/",
            "type": "link"
        },
        {
            "content": "http://img1.joyreactor.cc/pics/post/%D0%BA%D0%B0%D1%80%D1%82%D0%B8%D0%BD%D0%BA%D0%B0-%D1%81-%D1%82%D0%B5%D0%BA%D1%81%D1%82%D0%BE%D0%BC-%D0%B5%D0%B4%D0%B0-%D1%81%D1%8B%D1%80-%D0%BA%D0%BE%D0%BB%D0%B1%D0%B0%D1%81%D0%B0-5769159.jpeg",
            "type": "image"
        },
        {
            "content": "http://img0.joyreactor.cc/pics/post/%D0%B3%D0%B8%D1%84%D0%BA%D0%B8-%D0%B6%D0%B8%D0%B2%D0%BD%D0%BE%D1%81%D1%82%D1%8C-%D0%BA%D0%BE%D1%82%D1%8D-%D1%81%D0%BE%D0%B1%D0%B0%D0%BA%D0%B0-5769128.gif",
            "type": "image"
        },
        {
            "content": "http://img1.joyreactor.cc/pics/post/%D0%BA%D1%83%D1%81%D1%8C-%D0%B6%D0%B8%D0%B2%D0%BD%D0%BE%D1%81%D1%82%D1%8C-%D0%BA%D0%BE%D1%82%D1%94-%D0%B3%D0%B8%D1%84%D0%BA%D0%B0-5768427.gif",
            "type": "image"
        },
        {
            "content": "http://img1.joyreactor.cc/pics/post/%D0%BA%D0%BE%D1%82%D1%8D-%D0%B3%D0%B8%D1%84%D0%BA%D0%B8-5769403.gif",
            "type": "image"
        },
        {
            "content": "http://joyreactor.cc/post/4267833",
            "type": "link"
        },
        {
            "content": "http://img0.joyreactor.cc/pics/post/%D0%B3%D0%B8%D1%84%D0%BA%D0%B8-%D0%BC%D0%B8%D0%BB%D0%BE%D1%82%D0%B0-%D1%89%D0%B5%D0%BD%D0%BE%D0%BA-%D0%B6%D0%B5%D1%80%D0%B5%D0%B1%D0%B5%D0%BD%D0%BE%D0%BA-5770308.gif",
            "type": "image"
        },
        {
            "content": "http://img1.joyreactor.cc/pics/post/%D0%9B%D0%B8%D1%81%D0%B0-%D1%84%D1%8D%D0%BD%D0%B4%D0%BE%D0%BC%D1%8B-%D0%B4%D0%BE%D0%BC%D0%B0%D1%88%D0%BD%D1%8F%D1%8F-%D0%BB%D0%B8%D1%81%D0%B0-%D0%B4%D0%B5%D0%B2%D0%BE%D1%87%D0%BA%D0%B0-5769527.jpeg",
            "type": "image"
        },
        {
            "content": "http://img1.joyreactor.cc/pics/post/%D0%B3%D0%B8%D1%84%D0%BA%D0%B8-%D1%89%D0%B5%D0%BD%D0%BA%D0%B8-%D0%BA%D1%83%D1%80%D0%B8%D1%86%D0%B0-%D0%BF%D0%BE%D0%B4%D1%81%D1%82%D0%B0%D0%B2%D0%BA%D0%B0-5770889.gif",
            "type": "image"
        },
        {
            "content": "http://img1.joyreactor.cc/pics/post/Anime-%D1%84%D1%8D%D0%BD%D0%B4%D0%BE%D0%BC%D1%8B-roonhee-5774039.jpeg",
            "type": "image"
        },
        {
            "content": "https://coub.com/view/2a5uy9",
            "type": "link"
        },
        {
            "content": "http://img0.joyreactor.cc/pics/post/%D0%BA%D0%BE%D1%82%D1%8D-%D0%B6%D0%B8%D0%B2%D0%BD%D0%BE%D1%81%D1%82%D1%8C-5777946.jpeg",
            "type": "image"
        },
        {
            "content": "http://img1.joyreactor.cc/pics/post/%D0%B3%D0%B8%D1%84%D0%BA%D0%B8-%D0%BF%D0%B0%D0%BD%D0%B4%D1%8B-%D0%9F%D1%83%D1%88%D0%B8%D1%81%D1%82%D1%8B%D0%B5-%D0%B6%D0%BE%D0%BF%D0%BA%D0%B8-5778353.gif",
            "type": "image"
        },
        {
            "content": "http://img1.joyreactor.cc/pics/post/%D0%B3%D0%B8%D1%84%D0%BA%D0%B8-%D0%BA%D0%BE%D1%82%D0%B5%D0%B9%D0%BA%D0%B0-%D0%BB%D0%B0%D0%BF%D0%BA%D0%B8-5777429.gif",
            "type": "image"
        },
        {
            "content": "http://img1.joyreactor.cc/pics/post/%D0%B3%D0%B8%D1%84%D0%BA%D0%B8-%D0%BA%D0%BE%D1%82%D1%8D-%D0%BA%D0%BE%D0%BD%D0%B5%D1%86-%D1%81%D0%B2%D0%B5%D1%82%D0%B0-5776769.gif",
            "type": "image"
        },
        {
            "content": "http://img1.joyreactor.cc/pics/post/%D0%B3%D0%B8%D1%84%D0%BA%D0%B8-%D0%B6%D0%B8%D0%B2%D0%BD%D0%BE%D1%81%D1%82%D1%8C-%D0%9A%D0%A0%D0%A1-%D0%A7%D0%B5%D1%81%D0%B0%D0%BB%D0%BA%D0%B0-5778623.gif",
            "type": "image"
        },
        {
            "content": "https://i.pinimg.com/564x/4e/c5/a6/4ec5a6828619f7419fa5c9306f82941a.jpg",
            "type": "image"
        },
        {
            "content": "http://img0.joyreactor.cc/pics/post/%D0%B3%D0%B8%D1%84%D0%BA%D0%B8-%D0%BF%D0%B5%D1%81%D0%B5%D0%BB%D1%8C-5779732.gif",
            "type": "image"
        },
        {
            "content": "https://coub.com/view/2akhaj",
            "type": "link"
        },
        {
            "content": "https://coub.com/view/2afryt",
            "type": "link"
        },
        {
            "content": "http://img0.joyreactor.cc/pics/post/%D0%BA%D0%BE%D1%82%D1%8D-%D0%BF%D0%B5%D1%81%D0%BE%D1%87%D0%BD%D0%B8%D1%86%D0%B0-5781478.jpeg",
            "type": "image"
        },
        {
            "content": "http://img1.joyreactor.cc/pics/post/%D1%81%D0%BE%D0%B1%D0%B0%D0%BA%D0%B5%D0%BD-%D0%BA%D0%BE%D1%82%D1%8D-5781189.jpeg",
            "type": "image"
        },
        {
            "content": "http://img1.joyreactor.cc/pics/post/%D0%B3%D0%B8%D1%84%D0%BA%D0%B8-%D0%BF%D0%B5%D1%81%D0%BE%D1%87%D0%BD%D0%B8%D1%86%D0%B0-%D0%BA%D0%BE%D1%82%D1%8D-5781577.gif",
            "type": "image"
        },
        {
            "content": "http://img0.joyreactor.cc/pics/post/%D1%84%D0%BE%D1%82%D0%BE-%D0%B1%D0%B5%D0%B3%D0%B5%D0%BC%D0%BE%D1%82%D0%B8%D0%BA%D0%B8-%D0%B4%D0%BB%D0%B8%D0%BD%D0%BD%D0%BE%D0%BF%D0%BE%D1%81%D1%82-5782096.jpeg",
            "type": "image"
        },
        {
            "content": "http://joyreactor.cc/post/4275275",
            "type": "link"
        },
        {
            "content": "http://img0.joyreactor.cc/pics/post/%D1%84%D0%BE%D1%82%D0%BE%D0%BA%D0%BE%D0%BD%D0%BA%D1%83%D1%80%D1%81-%D0%9B%D0%B8%D1%81%D0%B0-%D1%84%D1%8D%D0%BD%D0%B4%D0%BE%D0%BC%D1%8B-%D0%B6%D0%B8%D0%B2%D0%BD%D0%BE%D1%81%D1%82%D1%8C-5782972.jpeg",
            "type": "image"
        },
        {
            "content": "http://img0.joyreactor.cc/pics/post/%D0%B3%D0%B8%D1%84%D0%BA%D0%B8-%D0%B6%D0%B8%D0%B2%D0%BD%D0%BE%D1%81%D1%82%D1%8C-%D0%BA%D0%BE%D1%82%D1%8D-%D1%81%D0%BE%D0%B1%D0%B0%D0%BA%D0%B0-5784810.gif",
            "type": "image"
        },
        {
            "content": "http://img0.joyreactor.cc/pics/post/%D0%B3%D0%B8%D1%84%D0%BA%D0%B8-%D0%BA%D0%BE%D1%82%D1%8D-%D1%80%D0%B5%D0%B2%D0%BD%D0%BE%D1%81%D1%82%D1%8C-5785088.gif",
            "type": "image"
        }
    ]
}